selenium_linux/__init__.py
selenium_linux/common/__init__.py
selenium_linux/common/exceptions.py
selenium_linux/webdriver/__init__.py
selenium_linux/webdriver/android/__init__.py
selenium_linux/webdriver/android/webdriver.py
selenium_linux/webdriver/blackberry/__init__.py
selenium_linux/webdriver/blackberry/webdriver.py
selenium_linux/webdriver/chrome/__init__.py
selenium_linux/webdriver/chrome/options.py
selenium_linux/webdriver/chrome/remote_connection.py
selenium_linux/webdriver/chrome/service.py
selenium_linux/webdriver/chrome/webdriver.py
selenium_linux/webdriver/common/__init__.py
selenium_linux/webdriver/common/action_chains.py
selenium_linux/webdriver/common/alert.py
selenium_linux/webdriver/common/by.py
selenium_linux/webdriver/common/desired_capabilities.py
selenium_linux/webdriver/common/keys.py
selenium_linux/webdriver/common/proxy.py
selenium_linux/webdriver/common/service.py
selenium_linux/webdriver/common/touch_actions.py
selenium_linux/webdriver/common/utils.py
selenium_linux/webdriver/common/actions/__init__.py
selenium_linux/webdriver/common/actions/action_builder.py
selenium_linux/webdriver/common/actions/input_device.py
selenium_linux/webdriver/common/actions/interaction.py
selenium_linux/webdriver/common/actions/key_actions.py
selenium_linux/webdriver/common/actions/key_input.py
selenium_linux/webdriver/common/actions/mouse_button.py
selenium_linux/webdriver/common/actions/pointer_actions.py
selenium_linux/webdriver/common/actions/pointer_input.py
selenium_linux/webdriver/common/html5/__init__.py
selenium_linux/webdriver/common/html5/application_cache.py
selenium_linux/webdriver/edge/__init__.py
selenium_linux/webdriver/edge/options.py
selenium_linux/webdriver/edge/service.py
selenium_linux/webdriver/edge/webdriver.py
selenium_linux/webdriver/firefox/__init__.py
selenium_linux/webdriver/firefox/extension_connection.py
selenium_linux/webdriver/firefox/firefox_binary.py
selenium_linux/webdriver/firefox/firefox_profile.py
selenium_linux-3.144.13.dist-info/METADATA
selenium_linux-3.144.13.dist-info/WHEEL
selenium_linux-3.144.13.dist-info/top_level.txt
selenium_linux-3.144.13.dist-info/RECORD
